<?xml version="1.0" encoding="UTF-8" ?>
<!DOCTYPE mapper PUBLIC "-//mybatis.org//DTD Mapper 3.0//EN" "http://mybatis.org/dtd/mybatis-3-mapper.dtd" >
<mapper namespace="sy.dao.ProductMapper" >
  <resultMap id="BaseResultMap" type="sy.model.Product" >
    <!--
      WARNING - @mbggenerated
      This element is automatically generated by MyBatis Generator, do not modify.
      This element was generated on Wed Mar 30 09:24:21 CST 2016.
    -->
    <id column="id" property="id" jdbcType="INTEGER" />
    <result column="proname" property="proname" jdbcType="VARCHAR" />
    <result column="prono" property="prono" jdbcType="VARCHAR" />
    <result column="img" property="img" jdbcType="VARCHAR" />
    <result column="price" property="price" jdbcType="VARCHAR" />
    <result column="field1" property="field1" jdbcType="VARCHAR" />
    <result column="field2" property="field2" jdbcType="VARCHAR" />
    <result column="field3" property="field3" jdbcType="VARCHAR" />
    <result column="field4" property="field4" jdbcType="VARCHAR" />
    <result column="field5" property="field5" jdbcType="VARCHAR" />
    <result column="field6" property="field6" jdbcType="VARCHAR" />
    <result column="field7" property="field7" jdbcType="VARCHAR" />
    <result column="field8" property="field8" jdbcType="VARCHAR" />
    <result column="field9" property="field9" jdbcType="VARCHAR" />
    <result column="field10" property="field10" jdbcType="VARCHAR" />
    <result column="protype" property="protype" jdbcType="VARCHAR" />
    <result column="delstatus" property="delstatus" jdbcType="VARCHAR" />
  </resultMap>
  <resultMap id="ResultMapWithBLOBs" type="sy.model.Product" extends="BaseResultMap" >
    <!--
      WARNING - @mbggenerated
      This element is automatically generated by MyBatis Generator, do not modify.
      This element was generated on Wed Mar 30 09:24:21 CST 2016.
    -->
    <result column="remark" property="remark" jdbcType="LONGVARCHAR" />
  </resultMap>
  <sql id="Base_Column_List" >
    <!--
      WARNING - @mbggenerated
      This element is automatically generated by MyBatis Generator, do not modify.
      This element was generated on Wed Mar 30 09:24:21 CST 2016.
    -->
    id, proname, prono, img, price, field1, field2, field3, field4, field5, field6, field7, 
    field8, field9, field10, protype, delstatus
  </sql>
  <sql id="Blob_Column_List" >
    <!--
      WARNING - @mbggenerated
      This element is automatically generated by MyBatis Generator, do not modify.
      This element was generated on Wed Mar 30 09:24:21 CST 2016.
    -->
    remark
  </sql>
  <select id="selectByPrimaryKey" resultMap="ResultMapWithBLOBs" parameterType="java.lang.Integer" >
    <!--
      WARNING - @mbggenerated
      This element is automatically generated by MyBatis Generator, do not modify.
      This element was generated on Wed Mar 30 09:24:21 CST 2016.
    -->
    select 
    <include refid="Base_Column_List" />
    ,
    <include refid="Blob_Column_List" />
    from product
    where id = #{id,jdbcType=INTEGER}
  </select>
  <delete id="deleteByPrimaryKey" parameterType="java.lang.Integer" >
    <!--
      WARNING - @mbggenerated
      This element is automatically generated by MyBatis Generator, do not modify.
      This element was generated on Wed Mar 30 09:24:21 CST 2016.
    -->
    delete from product
    where id = #{id,jdbcType=INTEGER}
  </delete>
  <insert id="insert" parameterType="sy.model.Product" >
    <!--
      WARNING - @mbggenerated
      This element is automatically generated by MyBatis Generator, do not modify.
      This element was generated on Wed Mar 30 09:24:21 CST 2016.
    -->
    insert into product (id, proname, prono, 
      img, price, field1, 
      field2, field3, field4, 
      field5, field6, field7, 
      field8, field9, field10, 
      protype, delstatus, remark
      )
    values (#{id,jdbcType=INTEGER}, #{proname,jdbcType=VARCHAR}, #{prono,jdbcType=VARCHAR}, 
      #{img,jdbcType=VARCHAR}, #{price,jdbcType=VARCHAR}, #{field1,jdbcType=VARCHAR}, 
      #{field2,jdbcType=VARCHAR}, #{field3,jdbcType=VARCHAR}, #{field4,jdbcType=VARCHAR}, 
      #{field5,jdbcType=VARCHAR}, #{field6,jdbcType=VARCHAR}, #{field7,jdbcType=VARCHAR}, 
      #{field8,jdbcType=VARCHAR}, #{field9,jdbcType=VARCHAR}, #{field10,jdbcType=VARCHAR}, 
      #{protype,jdbcType=VARCHAR}, #{delstatus,jdbcType=VARCHAR}, #{remark,jdbcType=LONGVARCHAR}
      )
  </insert>
  <insert id="insertSelective" parameterType="sy.model.Product" >
    <!--
      WARNING - @mbggenerated
      This element is automatically generated by MyBatis Generator, do not modify.
      This element was generated on Wed Mar 30 09:24:21 CST 2016.
    -->
    insert into product
    <trim prefix="(" suffix=")" suffixOverrides="," >
      <if test="id != null" >
        id,
      </if>
      <if test="proname != null" >
        proname,
      </if>
      <if test="prono != null" >
        prono,
      </if>
      <if test="img != null" >
        img,
      </if>
      <if test="price != null" >
        price,
      </if>
      <if test="field1 != null" >
        field1,
      </if>
      <if test="field2 != null" >
        field2,
      </if>
      <if test="field3 != null" >
        field3,
      </if>
      <if test="field4 != null" >
        field4,
      </if>
      <if test="field5 != null" >
        field5,
      </if>
      <if test="field6 != null" >
        field6,
      </if>
      <if test="field7 != null" >
        field7,
      </if>
      <if test="field8 != null" >
        field8,
      </if>
      <if test="field9 != null" >
        field9,
      </if>
      <if test="field10 != null" >
        field10,
      </if>
      <if test="protype != null" >
        protype,
      </if>
      <if test="delstatus != null" >
        delstatus,
      </if>
      <if test="remark != null" >
        remark,
      </if>
    </trim>
    <trim prefix="values (" suffix=")" suffixOverrides="," >
      <if test="id != null" >
        #{id,jdbcType=INTEGER},
      </if>
      <if test="proname != null" >
        #{proname,jdbcType=VARCHAR},
      </if>
      <if test="prono != null" >
        #{prono,jdbcType=VARCHAR},
      </if>
      <if test="img != null" >
        #{img,jdbcType=VARCHAR},
      </if>
      <if test="price != null" >
        #{price,jdbcType=VARCHAR},
      </if>
      <if test="field1 != null" >
        #{field1,jdbcType=VARCHAR},
      </if>
      <if test="field2 != null" >
        #{field2,jdbcType=VARCHAR},
      </if>
      <if test="field3 != null" >
        #{field3,jdbcType=VARCHAR},
      </if>
      <if test="field4 != null" >
        #{field4,jdbcType=VARCHAR},
      </if>
      <if test="field5 != null" >
        #{field5,jdbcType=VARCHAR},
      </if>
      <if test="field6 != null" >
        #{field6,jdbcType=VARCHAR},
      </if>
      <if test="field7 != null" >
        #{field7,jdbcType=VARCHAR},
      </if>
      <if test="field8 != null" >
        #{field8,jdbcType=VARCHAR},
      </if>
      <if test="field9 != null" >
        #{field9,jdbcType=VARCHAR},
      </if>
      <if test="field10 != null" >
        #{field10,jdbcType=VARCHAR},
      </if>
      <if test="protype != null" >
        #{protype,jdbcType=VARCHAR},
      </if>
      <if test="delstatus != null" >
        #{delstatus,jdbcType=VARCHAR},
      </if>
      <if test="remark != null" >
        #{remark,jdbcType=LONGVARCHAR},
      </if>
    </trim>
  </insert>
  <update id="updateByPrimaryKeySelective" parameterType="sy.model.Product" >
    <!--
      WARNING - @mbggenerated
      This element is automatically generated by MyBatis Generator, do not modify.
      This element was generated on Wed Mar 30 09:24:21 CST 2016.
    -->
    update product
    <set >
      <if test="proname != null" >
        proname = #{proname,jdbcType=VARCHAR},
      </if>
      <if test="prono != null" >
        prono = #{prono,jdbcType=VARCHAR},
      </if>
      <if test="img != null" >
        img = #{img,jdbcType=VARCHAR},
      </if>
      <if test="price != null" >
        price = #{price,jdbcType=VARCHAR},
      </if>
      <if test="field1 != null" >
        field1 = #{field1,jdbcType=VARCHAR},
      </if>
      <if test="field2 != null" >
        field2 = #{field2,jdbcType=VARCHAR},
      </if>
      <if test="field3 != null" >
        field3 = #{field3,jdbcType=VARCHAR},
      </if>
      <if test="field4 != null" >
        field4 = #{field4,jdbcType=VARCHAR},
      </if>
      <if test="field5 != null" >
        field5 = #{field5,jdbcType=VARCHAR},
      </if>
      <if test="field6 != null" >
        field6 = #{field6,jdbcType=VARCHAR},
      </if>
      <if test="field7 != null" >
        field7 = #{field7,jdbcType=VARCHAR},
      </if>
      <if test="field8 != null" >
        field8 = #{field8,jdbcType=VARCHAR},
      </if>
      <if test="field9 != null" >
        field9 = #{field9,jdbcType=VARCHAR},
      </if>
      <if test="field10 != null" >
        field10 = #{field10,jdbcType=VARCHAR},
      </if>
      <if test="protype != null" >
        protype = #{protype,jdbcType=VARCHAR},
      </if>
      <if test="delstatus != null" >
        delstatus = #{delstatus,jdbcType=VARCHAR},
      </if>
      <if test="remark != null" >
        remark = #{remark,jdbcType=LONGVARCHAR},
      </if>
    </set>
    where id = #{id,jdbcType=INTEGER}
  </update>
  <update id="updateByPrimaryKeyWithBLOBs" parameterType="sy.model.Product" >
    <!--
      WARNING - @mbggenerated
      This element is automatically generated by MyBatis Generator, do not modify.
      This element was generated on Wed Mar 30 09:24:21 CST 2016.
    -->
    update product
    set proname = #{proname,jdbcType=VARCHAR},
      prono = #{prono,jdbcType=VARCHAR},
      img = #{img,jdbcType=VARCHAR},
      price = #{price,jdbcType=VARCHAR},
      field1 = #{field1,jdbcType=VARCHAR},
      field2 = #{field2,jdbcType=VARCHAR},
      field3 = #{field3,jdbcType=VARCHAR},
      field4 = #{field4,jdbcType=VARCHAR},
      field5 = #{field5,jdbcType=VARCHAR},
      field6 = #{field6,jdbcType=VARCHAR},
      field7 = #{field7,jdbcType=VARCHAR},
      field8 = #{field8,jdbcType=VARCHAR},
      field9 = #{field9,jdbcType=VARCHAR},
      field10 = #{field10,jdbcType=VARCHAR},
      protype = #{protype,jdbcType=VARCHAR},
      delstatus = #{delstatus,jdbcType=VARCHAR},
      remark = #{remark,jdbcType=LONGVARCHAR}
    where id = #{id,jdbcType=INTEGER}
  </update>
  <update id="updateByPrimaryKey" parameterType="sy.model.Product" >
    <!--
      WARNING - @mbggenerated
      This element is automatically generated by MyBatis Generator, do not modify.
      This element was generated on Wed Mar 30 09:24:21 CST 2016.
    -->
    update product
    set proname = #{proname,jdbcType=VARCHAR},
      prono = #{prono,jdbcType=VARCHAR},
      img = #{img,jdbcType=VARCHAR},
      price = #{price,jdbcType=VARCHAR},
      field1 = #{field1,jdbcType=VARCHAR},
      field2 = #{field2,jdbcType=VARCHAR},
      field3 = #{field3,jdbcType=VARCHAR},
      field4 = #{field4,jdbcType=VARCHAR},
      field5 = #{field5,jdbcType=VARCHAR},
      field6 = #{field6,jdbcType=VARCHAR},
      field7 = #{field7,jdbcType=VARCHAR},
      field8 = #{field8,jdbcType=VARCHAR},
      field9 = #{field9,jdbcType=VARCHAR},
      field10 = #{field10,jdbcType=VARCHAR},
      protype = #{protype,jdbcType=VARCHAR},
      delstatus = #{delstatus,jdbcType=VARCHAR}
    where id = #{id,jdbcType=INTEGER}
  </update>
</mapper>